ciou/__init__.py
ciou/color/__init__.py
ciou/color/__main__.py
ciou/color/_color.py
ciou/color/_dynamic.py
ciou/progress/__init__.py
ciou/progress/_config.py
ciou/progress/_message.py
ciou/progress/_progress.py
ciou/progress/_renderer.py
ciou/snapshot/__init__.py
ciou/terminal/__init__.py
ciou/terminal/_windows.py
ciou/time/__init__.py
ciou/time/__main__.py
ciou/time/_ticker.py
ciou/time/_timestamp.py
ciou/types/__init__.py
ciou-0.6.1.dist-info/LICENSE
ciou-0.6.1.dist-info/METADATA
ciou-0.6.1.dist-info/WHEEL
ciou-0.6.1.dist-info/top_level.txt
ciou-0.6.1.dist-info/RECORD
