Metadata-Version: 2.1
Name: ciou
Version: 0.6.1
Summary: CLI input and output utils.
Author: Toni Kangas
License: MIT License
Project-URL: Homepage, https://github.com/kangasta/ciou
Project-URL: Repository, https://github.com/kangasta/ciou.git
Project-URL: Documentation, https://kangasta.github.io/yaml_requests/
Classifier: Programming Language :: Python :: 3
Classifier: License :: OSI Approved :: MIT License
Classifier: Operating System :: OS Independent
Requires-Python: >=3.8
License-File: LICENSE
